{
  "parent": "compressedores:craftcompressed",
  "display": {
    "icon": {
      "item": "compressedores:blockgold.double"
    },
    "title": {
      "translate": "Double Down"
    },
    "description": {
      "translate": "Reach Compression Level 2"
    },
    "frame": "task",
    "show_toast": true,
    "announce_to_chat": true,
    "hidden": false,
    "background": "minecraft:textures/gui/advancements/backgrounds/stone.png"
  },
  "criteria": {
    "Andesite": {
      "trigger": "minecraft:inventory_changed",
      "conditions": {
        "items": [
          {
            "item": "compressedores:blockandesite.double"
          }
        ]
      }
    },
    "Clay": {
      "trigger": "minecraft:inventory_changed",
      "conditions": {
        "items": [
          {
            "item": "compressedores:blockclay.double"
          }
        ]
      }
    },
    "Coal": {
      "trigger": "minecraft:inventory_changed",
      "conditions": {
        "items": [
          {
            "item": "compressedores:blockcoal.double"
          }
        ]
      }
    },
    "Cobble": {
      "trigger": "minecraft:inventory_changed",
      "conditions": {
        "items": [
          {
            "item": "compressedores:blockcobble.double"
          }
        ]
      }
    },
    "Diamond": {
      "trigger": "minecraft:inventory_changed",
      "conditions": {
        "items": [
          {
            "item": "compressedores:blockdiamond.double"
          }
        ]
      }
    },
    "Diorite": {
      "trigger": "minecraft:inventory_changed",
      "conditions": {
        "items": [
          {
            "item": "compressedores:blockdiorite.double"
          }
        ]
      }
    },
    "Dirt": {
      "trigger": "minecraft:inventory_changed",
      "conditions": {
        "items": [
          {
            "item": "compressedores:blockdirt.double"
          }
        ]
      }
    },
    "Emerald": {
      "trigger": "minecraft:inventory_changed",
      "conditions": {
        "items": [
          {
            "item": "compressedores:blockemerald.double"
          }
        ]
      }
    },
    "Gold": {
      "trigger": "minecraft:inventory_changed",
      "conditions": {
        "items": [
          {
            "item": "compressedores:blockgold.double"
          }
        ]
      }
    },
    "Granite": {
      "trigger": "minecraft:inventory_changed",
      "conditions": {
        "items": [
          {
            "item": "compressedores:blockgranite.double"
          }
        ]
      }
    },
    "Gravel": {
      "trigger": "minecraft:inventory_changed",
      "conditions": {
        "items": [
          {
            "item": "compressedores:blockgravel.double"
          }
        ]
      }
    },
    "Iron": {
      "trigger": "minecraft:inventory_changed",
      "conditions": {
        "items": [
          {
            "item": "compressedores:blockiron.double"
          }
        ]
      }
    },
    "Lapis": {
      "trigger": "minecraft:inventory_changed",
      "conditions": {
        "items": [
          {
            "item": "compressedores:blocklapis.double"
          }
        ]
      }
    },
    "Quartz": {
      "trigger": "minecraft:inventory_changed",
      "conditions": {
        "items": [
          {
            "item": "compressedores:blockquartz.double"
          }
        ]
      }
    },
    "Redstone": {
      "trigger": "minecraft:inventory_changed",
      "conditions": {
        "items": [
          {
            "item": "compressedores:blockredstone.double"
          }
        ]
      }
    },
    "Sand": {
      "trigger": "minecraft:inventory_changed",
      "conditions": {
        "items": [
          {
            "item": "compressedores:blocksand.double"
          }
        ]
      }
    }
  },
  "requirements": [
    [
      "Andesite",
      "Clay",
      "Coal",
      "Cobble",
      "Diamond",
      "Diorite",
      "Dirt",
      "Emerald",
      "Gold",
      "Granite",
      "Gravel",
      "Iron",
      "Lapis",
      "Quartz",
      "Redstone",
      "Sand"
    ]
  ]
}