{
  "parent": "minecraft:recipes/root",
  "criteria": {
    "has_the_recipe": {
      "conditions": {
        "recipe": "compressedores:lapis.double.up"
      },
      "trigger": "minecraft:recipe_unlocked"
    },
    "lapis.double.up": {
      "conditions": {
        "items": [
          {
            "items": [
              "compressedores:blocklapis.double"
            ]
          }
        ]
      },
      "trigger": "minecraft:inventory_changed"
    }
  },
  "requirements": [
    [
      "lapis.double.up",
      "has_the_recipe"
    ]
  ],
  "rewards": {
    "recipes": [
      "compressedores:lapis.double.up"
    ]
  }
}