{
  "parent": "minecraft:recipes/root",
  "criteria": {
    "has_the_recipe": {
      "conditions": {
        "recipe": "compressedores:tuff.triple.up"
      },
      "trigger": "minecraft:recipe_unlocked"
    },
    "tuff.triple.up": {
      "conditions": {
        "items": [
          {
            "items": [
              "compressedores:blocktuff.triple"
            ]
          }
        ]
      },
      "trigger": "minecraft:inventory_changed"
    }
  },
  "requirements": [
    [
      "tuff.triple.up",
      "has_the_recipe"
    ]
  ],
  "rewards": {
    "recipes": [
      "compressedores:tuff.triple.up"
    ]
  }
}