{
  "parent": "minecraft:recipes/root",
  "criteria": {
    "cobble.compressed.up": {
      "conditions": {
        "items": [
          {
            "items": [
              "compressedores:blockcobble.compressed"
            ]
          }
        ]
      },
      "trigger": "minecraft:inventory_changed"
    },
    "has_the_recipe": {
      "conditions": {
        "recipe": "compressedores:cobble.compressed.up"
      },
      "trigger": "minecraft:recipe_unlocked"
    }
  },
  "requirements": [
    [
      "cobble.compressed.up",
      "has_the_recipe"
    ]
  ],
  "rewards": {
    "recipes": [
      "compressedores:cobble.compressed.up"
    ]
  },
  "sends_telemetry_event": false
}